fred_mc/__init__.py
fred_mc/hello.py
fred_mc/libFred.so
fred_mc-0.0.5.dist-info/METADATA
fred_mc-0.0.5.dist-info/WHEEL
fred_mc-0.0.5.dist-info/licenses/LICENSE
fred_mc-0.0.5.dist-info/RECORD
