Metadata-Version: 2.3
Name: fred_mc
Version: 0.0.5
Summary: FRED Monte Carlo platform
Project-URL: Homepage, https://www.fred-mc.org
Project-URL: Issues, https://github.com/Fred-org/FRED-docs/discussions
Author-email: FRED Collaboration <angelo.schiavi@uniroma1.it>
License-File: LICENSE
Classifier: License :: Other/Proprietary License
Classifier: Operating System :: MacOS :: MacOS X
Classifier: Operating System :: Microsoft :: Windows
Classifier: Operating System :: POSIX :: Linux
Classifier: Programming Language :: Python :: 3
Requires-Python: <4.0,>=3.10
